sumtool/__init__.py
sumtool/__main__.py
sumtool/apropos.py
sumtool/mainwindow.py
sumtool/common/__appinfo__.py
sumtool/common/__init__.py
sumtool/forms/__init__.py
sumtool/forms/about.py
sumtool/forms/uimain.py
checksum_gui-0.1.dist-info/LICENSE
checksum_gui-0.1.dist-info/METADATA
checksum_gui-0.1.dist-info/WHEEL
checksum_gui-0.1.dist-info/entry_points.txt
checksum_gui-0.1.dist-info/top_level.txt
checksum_gui-0.1.dist-info/RECORD
